stacket/Service.py
stacket/StacketClient.py
stacket/__init__.py
stacket/config.py
stacket/domain.py
stacket/errors.py
stacket-0.2.1.dist-info/LICENSE
stacket-0.2.1.dist-info/METADATA
stacket-0.2.1.dist-info/WHEEL
stacket-0.2.1.dist-info/top_level.txt
stacket-0.2.1.dist-info/RECORD
