Metadata-Version: 2.1
Name: stacket
Version: 0.2.1
Summary: Stacket API Wrapper
Home-page: https://github.com/simonmaribo/stacket-api-wrapper
Author: SIMON#1386
License: MIT
Requires-Python: >=3.6
License-File: LICENSE
